README.md
setup.py
tfshop/__init__.py
tfshop/attention.py
tfshop.egg-info/PKG-INFO
tfshop.egg-info/SOURCES.txt
tfshop.egg-info/dependency_links.txt
tfshop.egg-info/not-zip-safe
tfshop.egg-info/requires.txt
tfshop.egg-info/top_level.txt