Metadata-Version: 1.0
Name: tfshop
Version: 0.0.1
Summary: common tensorflow paradigms
Home-page: http://github.com/theSage21/tfshop
Author: Arjoonn Sharma
Author-email: arjoonn.94@gmail.com
License: UNKNOWN
Keywords: tfshop,tensorflow
Platform: UNKNOWN
